{
  "annotations": {
    "changelogDate": "20240718162257"
  },
  "applications": "*",
  "fields": [
    {
      "fieldName": "description",
      "fieldType": "byte[]",
      "fieldTypeBlobContent": "text"
    },
    {
      "fieldName": "createdAt",
      "fieldType": "Instant"
    },
    {
      "fieldName": "updateAt",
      "fieldType": "Instant"
    }
  ],
  "name": "Comment",
  "relationships": [
    {
      "otherEntityName": "person",
      "relationshipName": "person",
      "relationshipSide": "left",
      "relationshipType": "one-to-one"
    },
    {
      "otherEntityField": "name",
      "otherEntityName": "commentList",
      "relationshipName": "commentlist",
      "relationshipSide": "left",
      "relationshipType": "many-to-one"
    }
  ],
  "searchEngine": "no"
}
